{
  "week": "2026-W02",
  "createdAt": 1775851925910,
  "players": {
    "adam1276#eune": {
      "tier": "DIAMOND",
      "rank": "II",
      "lp": 62,
      "wins": 204,
      "losses": 185
    },
    "littlestjeff1#goyem": {
      "tier": "DIAMOND",
      "rank": "IV",
      "lp": 13,
      "wins": 107,
      "losses": 100
    },
    "la cabra#iii": {
      "tier": "DIAMOND",
      "rank": "IV",
      "lp": 0,
      "wins": 193,
      "losses": 187
    },
    "spirifan3#faker": {
      "tier": "EMERALD",
      "rank": "III",
      "lp": 71,
      "wins": 94,
      "losses": 73
    },
    "darwizzy#høes": {
      "tier": "EMERALD",
      "rank": "III",
      "lp": 37,
      "wins": 55,
      "losses": 46
    },
    "fåce#tap": {
      "tier": "EMERALD",
      "rank": "III",
      "lp": 29,
      "wins": 211,
      "losses": 198
    },
    "la cabra ii#qlawi": {
      "tier": "EMERALD",
      "rank": "IV",
      "lp": 88,
      "wins": 40,
      "losses": 35
    },
    "moroccan dealer#pimp": {
      "tier": "PLATINUM",
      "rank": "II",
      "lp": 96,
      "wins": 71,
      "losses": 71
    },
    "mohsh#eune": {
      "tier": "PLATINUM",
      "rank": "II",
      "lp": 69,
      "wins": 268,
      "losses": 273
    },
    "pas på#00007": {
      "tier": "PLATINUM",
      "rank": "IV",
      "lp": 57,
      "wins": 71,
      "losses": 69
    },
    "dårk#abo": {
      "tier": "GOLD",
      "rank": "III",
      "lp": 18,
      "wins": 13,
      "losses": 6
    },
    "milad#exe": {
      "tier": "BRONZE",
      "rank": "I",
      "lp": 35,
      "wins": 10,
      "losses": 6
    }
  }
}